text_classifier/BERT.py
text_classifier/TextClassifier.py
text_classifier/__init__.py
bert_text_classifier-0.0.1a2.dist-info/LICENSE
bert_text_classifier-0.0.1a2.dist-info/METADATA
bert_text_classifier-0.0.1a2.dist-info/WHEEL
bert_text_classifier-0.0.1a2.dist-info/top_level.txt
bert_text_classifier-0.0.1a2.dist-info/RECORD
